intake_ids/__init__.py
intake_ids/cache.py
intake_ids/catalog.py
intake_ids/connector_controller.py
intake_ids/connector_csv_source.py
intake_ids/debug.py
intake_ids/exceptions.py
intake_ids/sources.py
intake_ids/cli/__init__.py
intake_ids/cli/periodic.py
intake_ids/ids_information_model/__init__.py
intake_ids/ids_information_model/action.py
intake_ids/ids_information_model/artifact.py
intake_ids/ids_information_model/binary_operator.py
intake_ids/ids_information_model/constraint.py
intake_ids/ids_information_model/contract.py
intake_ids/ids_information_model/described.py
intake_ids/ids_information_model/duty.py
intake_ids/ids_information_model/ids_model.py
intake_ids/ids_information_model/left_operand.py
intake_ids/ids_information_model/permission.py
intake_ids/ids_information_model/prohibition.py
intake_ids/ids_information_model/rule.py
intake_ids/ids_information_model/typed_literal.py
intake_ids/usage_control/__init__.py
intake_ids/usage_control/contract.py
intake_ids/usage_control/contract_util.py
intake_ids/usage_control/exceptions.py
intake_ids/usage_control/pattern.py
intake_ids/usage_control/rule.py
intake_ids/usage_control/validation.py
intake_ids/vendor/__init__.py
intake_ids/vendor/idsapi.py
intake_ids-0.0.5.dist-info/LICENSE
intake_ids-0.0.5.dist-info/METADATA
intake_ids-0.0.5.dist-info/WHEEL
intake_ids-0.0.5.dist-info/entry_points.txt
intake_ids-0.0.5.dist-info/top_level.txt
intake_ids-0.0.5.dist-info/RECORD
