Metadata-Version: 2.1
Name: intake-ids
Version: 0.0.5
Summary: Intake plugin for local artifacts in IDS connectors.
Home-page: https://pypi.org/project/intake-ids/
Author: Omer Erdinc Yagmurlu
Author-email: omeryagmurlu@gmail.com
License: MIT
Project-URL: Documentation, https://pypi.org/project/intake-ids/
Project-URL: Source, https://git.scc.kit.edu/uqtlv/data-science-connector
Project-URL: Tracker, https://git.scc.kit.edu/uqtlv/data-science-connector
Requires-Python: >=3.10
License-File: LICENSE
Requires-Dist: intake (>=0.6.5)
Requires-Dist: pandas (>=1.4.3)
Requires-Dist: requests (>=2.28.1)
Requires-Dist: pydantic (>=1.10.1)
Requires-Dist: isodate (>=0.6.1)
Requires-Dist: appdirs (>=1.4.4)
